{
	"code": "LGV_BRE3",
	"label": "LGV BRE3",
	"urls": {},
	"color": {
		"default": "#A42626",
		"easy": "#66711F"
	},
	"timetable_pattern": [
		{
			"code": "LGV_BRE3_A_15",
			"label": "Default A Direction",
			"interval_minutes": 60,
			"departure_minute": 15,
			"service": "local",
			"infomessages": [],
			"lineflowstops": [
				{
					"station_ID": "FR_29232_0",
					"departure_minute": 0
				},
				{
					"station_ID": "FR_56098_0",
					"arrival_minute": 22,
					"departure_minute": 23
				},
				{
					"station_ID": "FR_56206_0",
					"arrival_minute": 41,
					"departure_minute": 42
				},
				{
					"station_ID": "FR_44007_0",
					"arrival_minute": 63,
					"departure_minute": 64
				},
				{
					"station_ID": "FR_35238_0",
					"arrival_minute": 92
				}
			]
		},
		{
			"code": "LGV_BRE3_R_45",
			"label": "Default R Direction",
			"interval_minutes": 60,
			"departure_minute": 45,
			"service": "local",
			"infomessages": [],
			"lineflowstops": [
				{
					"station_ID": "FR_35238_0",
					"departure_minute": 0
				},
				{
					"station_ID": "FR_44007_0",
					"arrival_minute": 28,
					"departure_minute": 29
				},
				{
					"station_ID": "FR_56206_0",
					"arrival_minute": 50,
					"departure_minute": 51
				},
				{
					"station_ID": "FR_56098_0",
					"arrival_minute": 69,
					"departure_minute": 70
				},
				{
					"station_ID": "FR_29232_0",
					"arrival_minute": 92
				}
			]
		}
	]
}